rvimage/collection_types.py
rvimage/converters.py
rvimage/domain.py
rvimage-0.1.4.dist-info/METADATA
rvimage-0.1.4.dist-info/WHEEL
rvimage-0.1.4.dist-info/top_level.txt
rvimage-0.1.4.dist-info/RECORD
